<templateSet group="laravel">
  <template name="emailfield" value="&lt;!--- $VALUE$ Field ---&gt;&#10;&lt;div class=&quot;form-group&quot;&gt;&#10;    {!! Form::label('$NAME$', '$VALUE$:') !!}&#10;    {!! Form::email('$NAME$', null, ['class' =&gt; 'form-control']) !!}&#10;&lt;/div&gt;" description="emailfield Email form field" toReformat="false" toShortenFQNames="true">
    <variable name="VALUE" expression="" defaultValue="" alwaysStopAt="true" />
    <variable name="NAME" expression="" defaultValue="" alwaysStopAt="true" />
    <context>
      <option name="HTML_TEXT" value="true" />
      <option name="HTML" value="true" />
      <option name="PHP" value="true" />
      <option name="PHP Comment" value="true" />
      <option name="PHP String Literal" value="true" />
    </context>
  </template>
  <template name="emailfield4" value="&lt;!--- $VALUE$ Field ---&gt;&#10;&lt;div class=&quot;form-group&quot;&gt;&#10;    {{ Form::label('$NAME$', '$VALUE$:') }}&#10;    {{ Form::email('$NAME$', null, ['class' =&gt; 'form-control']) }}&#10;&lt;/div&gt;" description="emailfield Email form field" toReformat="false" toShortenFQNames="true">
    <variable name="VALUE" expression="" defaultValue="" alwaysStopAt="true" />
    <variable name="NAME" expression="" defaultValue="" alwaysStopAt="true" />
    <context>
      <option name="HTML_TEXT" value="true" />
      <option name="HTML" value="true" />
      <option name="PHP" value="true" />
      <option name="PHP Comment" value="true" />
      <option name="PHP String Literal" value="true" />
    </context>
  </template>
  <template name="fc" value="{!! Form::close() !!}" description="fc Form close tag" toReformat="false" toShortenFQNames="true">
    <context>
      <option name="HTML_TEXT" value="true" />
      <option name="HTML" value="true" />
      <option name="PHP" value="true" />
      <option name="PHP Comment" value="true" />
      <option name="PHP String Literal" value="true" />
    </context>
  </template>
  <template name="fc4" value="{{ Form::close() }}" description="fc Form close tag" toReformat="false" toShortenFQNames="true">
    <context>
      <option name="HTML_TEXT" value="true" />
      <option name="HTML" value="true" />
      <option name="PHP" value="true" />
      <option name="PHP Comment" value="true" />
      <option name="PHP String Literal" value="true" />
    </context>
  </template>
  <template name="filefield" value="&lt;!--- $VALUE$ Field ---&gt;&#10;&lt;div class=&quot;form-group&quot;&gt;&#10;    {!! Form::label('$NAME$', '$VALUE$:') !!}&#10;    {!! Form::file('$NAME$', ['class' =&gt; 'btn btn-group']) !!}&#10;&lt;/div&gt;" description="filefield File form field" toReformat="false" toShortenFQNames="true">
    <variable name="VALUE" expression="" defaultValue="" alwaysStopAt="true" />
    <variable name="NAME" expression="" defaultValue="" alwaysStopAt="true" />
    <context>
      <option name="HTML_TEXT" value="true" />
      <option name="HTML" value="true" />
      <option name="PHP" value="true" />
      <option name="PHP Comment" value="true" />
      <option name="PHP String Literal" value="true" />
    </context>
  </template>
  <template name="filefield4" value="&lt;!--- $VALUE$ Field ---&gt;&#10;&lt;div class=&quot;form-group&quot;&gt;&#10;    {{ Form::label('$NAME$', '$VALUE$:') }}&#10;    {{ Form::file('$NAME$', ['class' =&gt; 'btn btn-group']) }}&#10;&lt;/div&gt;" description="filefield File form field" toReformat="false" toShortenFQNames="true">
    <variable name="VALUE" expression="" defaultValue="" alwaysStopAt="true" />
    <variable name="NAME" expression="" defaultValue="" alwaysStopAt="true" />
    <context>
      <option name="HTML_TEXT" value="true" />
      <option name="HTML" value="true" />
      <option name="PHP" value="true" />
      <option name="PHP Comment" value="true" />
      <option name="PHP String Literal" value="true" />
    </context>
  </template>
  <template name="fo" value="{!! Form::open() !!}" description="fo Form open tag" toReformat="false" toShortenFQNames="true">
    <context>
      <option name="HTML_TEXT" value="true" />
      <option name="HTML" value="true" />
      <option name="PHP" value="true" />
      <option name="PHP Comment" value="true" />
      <option name="PHP String Literal" value="true" />
    </context>
  </template>
  <template name="fo4" value="{{ Form::open() }}" description="fo Form open tag" toReformat="false" toShortenFQNames="true">
    <context>
      <option name="HTML_TEXT" value="true" />
      <option name="HTML" value="true" />
      <option name="PHP" value="true" />
      <option name="PHP Comment" value="true" />
      <option name="PHP String Literal" value="true" />
    </context>
  </template>
  <template name="hiddenfield" value="{!! Form::hidden('$NAME$', $VALUE$) !!}" description="hiddenfield Hidden form field" toReformat="false" toShortenFQNames="true">
    <variable name="NAME" expression="" defaultValue="" alwaysStopAt="true" />
    <variable name="VALUE" expression="" defaultValue="" alwaysStopAt="true" />
    <context>
      <option name="HTML_TEXT" value="true" />
      <option name="HTML" value="true" />
      <option name="PHP" value="true" />
      <option name="PHP Comment" value="true" />
      <option name="PHP String Literal" value="true" />
    </context>
  </template>
  <template name="hiddenfield4" value="{{ Form::hidden('$NAME$', $VALUE$) }}" description="hiddenfield Hidden form field" toReformat="false" toShortenFQNames="true">
    <variable name="NAME" expression="" defaultValue="" alwaysStopAt="true" />
    <variable name="VALUE" expression="" defaultValue="" alwaysStopAt="true" />
    <context>
      <option name="HTML_TEXT" value="true" />
      <option name="HTML" value="true" />
      <option name="PHP" value="true" />
      <option name="PHP Comment" value="true" />
      <option name="PHP String Literal" value="true" />
    </context>
  </template>
  <template name="passwordfield" value="&lt;!--- $VALUE$ Field ---&gt;&#10;&lt;div class=&quot;form-group&quot;&gt;&#10;    {!! Form::label('$NAME$', '$VALUE$:') !!}&#10;    {!! Form::password('$NAME$', ['class' =&gt; 'form-control']) !!}&#10;&lt;/div&gt;" description="passwordfield Password form field" toReformat="false" toShortenFQNames="true">
    <variable name="VALUE" expression="" defaultValue="" alwaysStopAt="true" />
    <variable name="NAME" expression="" defaultValue="" alwaysStopAt="true" />
    <context>
      <option name="HTML_TEXT" value="true" />
      <option name="HTML" value="true" />
      <option name="PHP" value="true" />
      <option name="PHP Comment" value="true" />
      <option name="PHP String Literal" value="true" />
    </context>
  </template>
  <template name="passwordfield4" value="&lt;!--- $VALUE$ Field ---&gt;&#10;&lt;div class=&quot;form-group&quot;&gt;&#10;    {{ Form::label('$NAME$', '$VALUE$:') }}&#10;    {{ Form::password('$NAME$', ['class' =&gt; 'form-control']) }}&#10;&lt;/div&gt;" description="passwordfield Password form field" toReformat="false" toShortenFQNames="true">
    <variable name="VALUE" expression="" defaultValue="" alwaysStopAt="true" />
    <variable name="NAME" expression="" defaultValue="" alwaysStopAt="true" />
    <context>
      <option name="HTML_TEXT" value="true" />
      <option name="HTML" value="true" />
      <option name="PHP" value="true" />
      <option name="PHP Comment" value="true" />
      <option name="PHP String Literal" value="true" />
    </context>
  </template>
  <template name="selectfield" value="&lt;!--- $VALUE$ Field ---&gt;&#10;&lt;div class=&quot;form-group&quot;&gt;&#10;    {!! Form::label('$NAME$', '$VALUE$:') !!}&#10;    {!! Form::select('$NAME$', [], null, ['class' =&gt; 'form-control']) !!}&#10;&lt;/div&gt;" description="Select field" toReformat="false" toShortenFQNames="true">
    <variable name="VALUE" expression="" defaultValue="" alwaysStopAt="true" />
    <variable name="NAME" expression="" defaultValue="" alwaysStopAt="true" />
    <context>
      <option name="HTML_TEXT" value="true" />
      <option name="HTML" value="true" />
      <option name="PHP" value="true" />
      <option name="PHP Comment" value="true" />
      <option name="PHP String Literal" value="true" />
    </context>
  </template>
  <template name="selectfield4" value="&lt;!--- $VALUE$ Field ---&gt;&#10;&lt;div class=&quot;form-group&quot;&gt;&#10;    {{ Form::label('$NAME$', '$VALUE$:') }}&#10;    {{ Form::select('$NAME$', [], null, ['class' =&gt; 'form-control']) }}&#10;&lt;/div&gt;" description="Select field" toReformat="false" toShortenFQNames="true">
    <variable name="VALUE" expression="" defaultValue="" alwaysStopAt="true" />
    <variable name="NAME" expression="" defaultValue="" alwaysStopAt="true" />
    <context>
      <option name="HTML_TEXT" value="true" />
      <option name="HTML" value="true" />
      <option name="PHP" value="true" />
      <option name="PHP Comment" value="true" />
      <option name="PHP String Literal" value="true" />
    </context>
  </template>
  <template name="submitfield" value="&lt;!--- $VALUE$ Field ---&gt;&#10;&lt;div class=&quot;form-group&quot;&gt;&#10;    {!! Form::submit('$NAME$', ['class' =&gt; 'btn btn-primary pull-right']) !!}&#10;&lt;/div&gt;" description="submitfield Submit form field" toReformat="false" toShortenFQNames="true">
    <variable name="VALUE" expression="" defaultValue="" alwaysStopAt="true" />
    <variable name="NAME" expression="" defaultValue="" alwaysStopAt="true" />
    <context>
      <option name="HTML_TEXT" value="true" />
      <option name="HTML" value="true" />
      <option name="PHP" value="true" />
      <option name="PHP Comment" value="true" />
      <option name="PHP String Literal" value="true" />
    </context>
  </template>
  <template name="submitfield4" value="&lt;!--- $VALUE$ Field ---&gt;&#10;&lt;div class=&quot;form-group&quot;&gt;&#10;    {{ Form::submit('$NAME$', ['class' =&gt; 'btn btn-primary pull-right']) }}&#10;&lt;/div&gt;" description="submitfield Submit form field" toReformat="false" toShortenFQNames="true">
    <variable name="VALUE" expression="" defaultValue="" alwaysStopAt="true" />
    <variable name="NAME" expression="" defaultValue="" alwaysStopAt="true" />
    <context>
      <option name="HTML_TEXT" value="true" />
      <option name="HTML" value="true" />
      <option name="PHP" value="true" />
      <option name="PHP Comment" value="true" />
      <option name="PHP String Literal" value="true" />
    </context>
  </template>
  <template name="textareafield" value="&lt;!--- $VALUE$ Field ---&gt;&#10;&lt;div class=&quot;form-group&quot;&gt;&#10;    {!! Form::label('$NAME$', '$VALUE$:') !!}&#10;    {!! Form::textarea('$NAME$', null, ['class' =&gt; 'form-control']) !!}&#10;&lt;/div&gt;" description="textareafield Text area form field" toReformat="false" toShortenFQNames="true">
    <variable name="VALUE" expression="" defaultValue="" alwaysStopAt="true" />
    <variable name="NAME" expression="" defaultValue="" alwaysStopAt="true" />
    <context>
      <option name="HTML_TEXT" value="true" />
      <option name="HTML" value="true" />
      <option name="PHP" value="true" />
      <option name="PHP Comment" value="true" />
      <option name="PHP String Literal" value="true" />
    </context>
  </template>
  <template name="textareafield4" value="&lt;!--- $VALUE$ Field ---&gt;&#10;&lt;div class=&quot;form-group&quot;&gt;&#10;    {{ Form::label('$NAME$', '$VALUE$:') }}&#10;    {{ Form::textarea('$NAME$', null, ['class' =&gt; 'form-control']) }}&#10;&lt;/div&gt;" description="textareafield Text area form field" toReformat="false" toShortenFQNames="true">
    <variable name="VALUE" expression="" defaultValue="" alwaysStopAt="true" />
    <variable name="NAME" expression="" defaultValue="" alwaysStopAt="true" />
    <context>
      <option name="HTML_TEXT" value="true" />
      <option name="HTML" value="true" />
      <option name="PHP" value="true" />
      <option name="PHP Comment" value="true" />
      <option name="PHP String Literal" value="true" />
    </context>
  </template>
  <template name="textfield" value="&lt;!--- $VALUE$ Field ---&gt;&#10;&lt;div class=&quot;form-group&quot;&gt;&#10;    {!! Form::label('$NAME$', '$VALUE$:') !!}&#10;    {!! Form::text('$NAME$', null, ['class' =&gt; 'form-control']) !!}&#10;&lt;/div&gt;" description="textfield Text form field" toReformat="false" toShortenFQNames="true">
    <variable name="VALUE" expression="" defaultValue="" alwaysStopAt="true" />
    <variable name="NAME" expression="" defaultValue="" alwaysStopAt="true" />
    <context>
      <option name="HTML_TEXT" value="true" />
      <option name="HTML" value="true" />
      <option name="PHP" value="true" />
      <option name="PHP Comment" value="true" />
      <option name="PHP String Literal" value="true" />
    </context>
  </template>
  <template name="textfield4" value="&lt;!--- $VALUE$ Field ---&gt;&#10;&lt;div class=&quot;form-group&quot;&gt;&#10;    {{ Form::label('$NAME$', '$VALUE$:') }}&#10;    {{ Form::text('$NAME$', null, ['class' =&gt; 'form-control']) }}&#10;&lt;/div&gt;" description="textfield Text form field" toReformat="false" toShortenFQNames="true">
    <variable name="VALUE" expression="" defaultValue="" alwaysStopAt="true" />
    <variable name="NAME" expression="" defaultValue="" alwaysStopAt="true" />
    <context>
      <option name="HTML_TEXT" value="true" />
      <option name="HTML" value="true" />
      <option name="PHP" value="true" />
      <option name="PHP Comment" value="true" />
      <option name="PHP String Literal" value="true" />
    </context>
  </template>
</templateSet>